setup.py
Fedora3.8_Utilities.egg-info/PKG-INFO
Fedora3.8_Utilities.egg-info/SOURCES.txt
Fedora3.8_Utilities.egg-info/dependency_links.txt
Fedora3.8_Utilities.egg-info/requires.txt
Fedora3.8_Utilities.egg-info/top_level.txt
legacy_fedora/__init__.py
legacy_fedora/app.py
legacy_fedora/forms.py
legacy_fedora/helpers.py
legacy_fedora/indexer.py
legacy_fedora/mapping.py
legacy_fedora/mods2json.py
legacy_fedora/repairer.py