Metadata-Version: 1.1
Name: Fedora3.8-Utilities
Version: 1.2.0
Summary: Utilities for legacy Fedora 3.8 repository
Home-page: https://github.com/Tutt-Library/fedora38-utilities
Author: Jeremy Nelson
Author-email: jermnelson@gmail.com
License: Apache2
Keywords: fedora3.8 library
Platform: UNKNOWN
Classifier: Development Status :: 5 - Production/Stable
Classifier: Intended Audience :: Other Audience
Classifier: License :: OSI Approved :: Apache Software License
Classifier: Operating System :: OS Independent
Classifier: Programming Language :: Python
Classifier: Programming Language :: Python :: 3.5
Classifier: Topic :: Internet :: WWW/HTTP :: Dynamic Content
Classifier: Topic :: Software Development :: Libraries :: Python Modules
